extrathick/__init__.py
extrathick/__main__.py
extrathick/threading.py
extrathick-0.2.3.dist-info/LICENSE.txt
extrathick-0.2.3.dist-info/METADATA
extrathick-0.2.3.dist-info/WHEEL
extrathick-0.2.3.dist-info/top_level.txt
extrathick-0.2.3.dist-info/RECORD
