Metadata-Version: 2.1
Name: extrathick
Version: 0.2.3
Summary: Common methods that I use all the time but don't necessarily feel they should be part of the standard library
Home-page: https://github.com/FoleyDiver/extrathick
Author: Steve Foley
Author-email: sfoley1988@gmail.com
License: GPLv2+
Download-URL: https://github.com/FoleyDiver/extrathick/archive/v0.2.3.tar.gz
Platform: UNKNOWN
Classifier: Development Status :: 3 - Alpha
Classifier: License :: OSI Approved :: GNU General Public License v2 or later (GPLv2+)
Classifier: Intended Audience :: Developers
Classifier: Programming Language :: Python :: 3.4
Classifier: Programming Language :: Python :: 3.5
Classifier: Programming Language :: Python :: 3.6
Requires-Dist: steov
